onlinebrief24/__init__.py
onlinebrief24/client.py
onlinebrief24-1.2.dist-info/LICENSE.txt
onlinebrief24-1.2.dist-info/METADATA
onlinebrief24-1.2.dist-info/WHEEL
onlinebrief24-1.2.dist-info/top_level.txt
onlinebrief24-1.2.dist-info/RECORD
