Metadata-Version: 2.1
Name: onlinebrief24
Version: 1.2
Summary: Python client for onlinebrief24.de - a German letter sending service.
Home-page: https://github.com/dajool/onlinebrief24
Author: Jochen Breuer
Author-email: breuer@dajool.com
License: MIT License
Keywords: pdf,mailing,letters,post
Platform: any
Requires-Dist: paramiko (>=1.15.3)
